README.txt
setup.py
Looppool.egg-info/PKG-INFO
Looppool.egg-info/SOURCES.txt
Looppool.egg-info/dependency_links.txt
Looppool.egg-info/requires.txt
Looppool.egg-info/top_level.txt
looppool/__init__.py
looppool/test.py
looppool/utility.py