Metadata-Version: 1.1
Name: Looppool
Version: 0.3.0
Summary: Tornado IO loop process pool with message passing
Home-page: https://bitbucket.org/saaj/looppool
Author: saaj
Author-email: mail@saaj.me
License: LGPL-2.1+
Keywords: python tornado multiprocessing process-pool io-loop
Platform: Any
Classifier: Topic :: Software Development :: Libraries
Classifier: Programming Language :: Python :: 3
Classifier: Programming Language :: Python :: 3.4
Classifier: Programming Language :: Python :: 3.5
Classifier: Intended Audience :: Developers
